sonar_mcp/__init__.py
sonar_mcp/__main__.py
sonar_mcp/context.py
sonar_mcp/instance_manager.py
sonar_mcp/py.typed
sonar_mcp/server.py
sonar_mcp/auth/__init__.py
sonar_mcp/auth/manager.py
sonar_mcp/client/__init__.py
sonar_mcp/client/sonar_client.py
sonar_mcp/config/__init__.py
sonar_mcp/config/models.py
sonar_mcp/models/__init__.py
sonar_mcp/prompts/__init__.py
sonar_mcp/prompts/code_review.py
sonar_mcp/prompts/quality_report.py
sonar_mcp/prompts/security_audit.py
sonar_mcp/resources/__init__.py
sonar_mcp/resources/issues.py
sonar_mcp/resources/metrics.py
sonar_mcp/resources/projects.py
sonar_mcp/schemas/__init__.py
sonar_mcp/schemas/base.py
sonar_mcp/schemas/instance.py
sonar_mcp/schemas/issue.py
sonar_mcp/schemas/metrics.py
sonar_mcp/schemas/project.py
sonar_mcp/schemas/quality_gate.py
sonar_mcp/schemas/rule.py
sonar_mcp/tasks/__init__.py
sonar_mcp/tasks/manager.py
sonar_mcp/tasks/models.py
sonar_mcp/tools/__init__.py
sonar_mcp/tools/categories.py
sonar_mcp/tools/client_helper.py
sonar_mcp/tools/instance.py
sonar_mcp/tools/issue.py
sonar_mcp/tools/metrics.py
sonar_mcp/tools/project.py
sonar_mcp/tools/quality_gate.py
sonar_mcp/tools/rules.py
sonar_mcp/tools/task.py
sonar_mcp/utils/__init__.py
sonar_mcp-1.1.0.dist-info/licenses/LICENSE
sonar_mcp-1.1.0.dist-info/METADATA
sonar_mcp-1.1.0.dist-info/WHEEL
sonar_mcp-1.1.0.dist-info/entry_points.txt
sonar_mcp-1.1.0.dist-info/top_level.txt
sonar_mcp-1.1.0.dist-info/RECORD
