Metadata-Version: 2.4
Name: sonar-mcp
Version: 1.1.0
Summary: MCP server for SonarQube code quality platform
Author: Wade Woolwine
License-Expression: MIT
Project-URL: Homepage, https://github.com/wadew/sonar-mcp
Project-URL: Documentation, https://github.com/wadew/sonar-mcp#documentation
Project-URL: Repository, https://github.com/wadew/sonar-mcp.git
Project-URL: Issues, https://github.com/wadew/sonar-mcp/issues
Project-URL: Changelog, https://github.com/wadew/sonar-mcp/blob/main/CHANGELOG.md
Keywords: mcp,sonarqube,code-quality,static-analysis
Classifier: Development Status :: 5 - Production/Stable
Classifier: Intended Audience :: Developers
Classifier: Operating System :: OS Independent
Classifier: Programming Language :: Python :: 3
Classifier: Programming Language :: Python :: 3.11
Classifier: Programming Language :: Python :: 3.12
Classifier: Programming Language :: Python :: 3.13
Classifier: Topic :: Software Development :: Quality Assurance
Classifier: Topic :: Software Development :: Testing
Classifier: Typing :: Typed
Requires-Python: >=3.11
License-File: LICENSE
Requires-Dist: mcp<2,>=1.25.0
Requires-Dist: httpx>=0.27.0
Requires-Dist: pydantic>=2.12.5
Requires-Dist: pyyaml>=6.0.2
Requires-Dist: structlog>=25.5.0
Requires-Dist: tenacity>=9.1.2
Requires-Dist: python-dotenv>=1.1.0
Provides-Extra: dev
Requires-Dist: pytest>=9.0.2; extra == "dev"
Requires-Dist: pytest-asyncio>=1.3.0; extra == "dev"
Requires-Dist: pytest-cov>=7.0.0; extra == "dev"
Requires-Dist: pytest-mock>=3.15.1; extra == "dev"
Requires-Dist: pytest-httpx>=0.35.0; extra == "dev"
Requires-Dist: ruff>=0.14.10; extra == "dev"
Requires-Dist: mypy>=1.19.1; extra == "dev"
Requires-Dist: bandit[toml]>=1.8.0; extra == "dev"
Requires-Dist: pip-audit>=2.9.0; extra == "dev"
Requires-Dist: build>=1.2.0; extra == "dev"
Requires-Dist: twine>=6.1.0; extra == "dev"
Requires-Dist: pre-commit>=4.0.0; extra == "dev"
Dynamic: license-file
